solvent_ai/__init__.py
solvent_ai/ai/__init__.py
solvent_ai/ai/anthropic/__init__.py
solvent_ai/ai/anthropic/client.py
solvent_ai/ai/base.py
solvent_ai/ai/context.py
solvent_ai/ai/factory.py
solvent_ai/ai/gemini/__init__.py
solvent_ai/ai/gemini/client.py
solvent_ai/ai/openai/__init__.py
solvent_ai/ai/openai/client.py
solvent_ai/ai/retry.py
solvent_ai/config/__init__.py
solvent_ai/config/logging_config.py
solvent_ai/config/settings.py
solvent_ai/git/__init__.py
solvent_ai/git/repository.py
solvent_ai/hook/__init__.py
solvent_ai/hook/evaluator.py
solvent_ai/hook/orchestrator.py
solvent_ai/main.py
solvent_ai/models/__init__.py
solvent_ai/models/file_info.py
solvent_ai/models/hook.py
solvent_ai/rules/__init__.py
solvent_ai/rules/context.py
solvent_ai/rules/ignore.py
solvent_ai-0.2.0.dist-info/WHEEL
solvent_ai-0.2.0.dist-info/entry_points.txt
solvent_ai-0.2.0.dist-info/METADATA
solvent_ai-0.2.0.dist-info/RECORD
