Metadata-Version: 2.3
Name: solvent-ai
Version: 0.2.0
Summary: AI-powered pre-commit hook for code review using multiple AI providers
License: MIT
Requires-Dist: anthropic>=0.72.1
Requires-Dist: gitpython>=3.1.45
Requires-Dist: google-genai>=1.49.0
Requires-Dist: openai>=2.7.2
Requires-Dist: pathspec>=0.12.1
Requires-Dist: pydantic>=2.12.4
Requires-Dist: pydantic-settings>=2.12.0
Requires-Python: >=3.10
